promptkit/__init__.py
promptkit/chatgpt/__init__.py
promptkit/chatgpt/response.py
promptkit/chatgpt/schema.py
promptkit/chatgpt/session.py
promptkit/config.py
promptkit/prompts/summarize.template
promptkit/tools/__init__.py
promptkit/tools/summarize.py
promptkit/utils/__init__.py
promptkit/utils/retry.py
promptkit/utils/template.py
promptkit-0.0.1.dist-info/METADATA
promptkit-0.0.1.dist-info/WHEEL
promptkit-0.0.1.dist-info/RECORD
