Metadata-Version: 2.1
Name: promptkit
Version: 0.0.1
Summary: Lightweight prompt engineering toolkit
License: MIT
Author: Shroominic
Author-email: pleurae-berets.0u@icloud.com
Requires-Python: >=3.11,<4.0
Classifier: License :: OSI Approved :: MIT License
Classifier: Programming Language :: Python :: 3
Classifier: Programming Language :: Python :: 3.11
Requires-Dist: openai (>=0.27.8,<0.28.0)
Requires-Dist: pydantic (==2.0)
Requires-Dist: python-dotenv (>=1.0.0,<2.0.0)
